video_download_play/__init__.py
video_download_play/video.py
video_download_play-0.0.1.dist-info/METADATA
video_download_play-0.0.1.dist-info/WHEEL
video_download_play-0.0.1.dist-info/licenses/LICENSE
video_download_play-0.0.1.dist-info/RECORD
